astrbot_canary_api/__init__.py
astrbot_canary_api/enums.py
astrbot_canary_api/interface.py
astrbot_canary_api/models.py
astrbot_canary_api/py.typed
astrbot_canary_api-0.1.0.dist-info/METADATA
astrbot_canary_api-0.1.0.dist-info/WHEEL
astrbot_canary_api-0.1.0.dist-info/entry_points.txt
astrbot_canary_api-0.1.0.dist-info/RECORD
