Metadata-Version: 2.4
Name: astrbot-canary-api
Version: 0.1.0
Summary: astrbot module canary api
Author-email: LIghtJUNction <LIghtJUNction.me@gmail.com>
Requires-Python: >=3.13.8
Requires-Dist: anyio>=4.11.0
Requires-Dist: dotenv>=0.9.9
Requires-Dist: pluggy>=1.6.0
Requires-Dist: pydantic>=2.12.0
Requires-Dist: sqlalchemy>=2.0.44
Requires-Dist: taskiq>=0.11.18
Requires-Dist: toml>=0.10.2
Requires-Dist: wrapt>=1.17.3
